README.md
setup.py
zomato_distribution_api/__init__.py
zomato_distribution_api/zomato_wrapper.py
zomato_distribution_api.egg-info/PKG-INFO
zomato_distribution_api.egg-info/SOURCES.txt
zomato_distribution_api.egg-info/dependency_links.txt
zomato_distribution_api.egg-info/not-zip-safe
zomato_distribution_api.egg-info/top_level.txt