Metadata-Version: 2.1
Name: zomato-distribution-api
Version: 0.2.3
Summary: provides wrapper for the zomato web api
Home-page: UNKNOWN
Author: Chetan Raj Rupakheti
Author-email: chetanrrk@gmail.com
License: UNKNOWN
Platform: UNKNOWN
Requires-Python: >=3
